syrius/__init__.py
syrius/__version__.py
syrius/api.py
syrius/exceptions.py
syrius/flow.py
syrius/types.py
syrius/commands/AWSPollyGenerateCommand.py
syrius/commands/AWSS3SaveObjectCommand.py
syrius/commands/AWSSESSendEmailCommand.py
syrius/commands/AnthropicCompletionCommand.py
syrius/commands/ArrayFilterByCommand.py
syrius/commands/ArrayKeyValueCommand.py
syrius/commands/ArrayLengthCommand.py
syrius/commands/ArrayOfKeyValueToArrayCommand.py
syrius/commands/ArrayReduceByKeyCommand.py
syrius/commands/ArraysGetKeyCommand.py
syrius/commands/ArraysKeyValueMergeCommand.py
syrius/commands/ArraysMergeByKeyCommand.py
syrius/commands/ArraysMergeCommand.py
syrius/commands/AzureCompletionCommand.py
syrius/commands/AzureTextToSpeechCommand.py
syrius/commands/BriaBackgroundGenerateCommand.py
syrius/commands/BriaLifeStyleProductShotImageCommand.py
syrius/commands/BriaProductShadowCommand.py
syrius/commands/CharactersCounterCommand.py
syrius/commands/CurrencyFormatterCommand.py
syrius/commands/ElevenlabsAddVoiceCommand.py
syrius/commands/ElevenlabsDeleteVoiceCommand.py
syrius/commands/ElevenlabsGetVoicesCommand.py
syrius/commands/ElevenlabsSoundEffectsCommand.py
syrius/commands/ElevenlabsTextToSpeechCommand.py
syrius/commands/ElevenlabsVoiceCloneCommand.py
syrius/commands/FilePublicUploadCommand.py
syrius/commands/FileTextExtractCommand.py
syrius/commands/FileUploadCommand.py
syrius/commands/GetFileNameCommand.py
syrius/commands/GoogleGeminiCommand.py
syrius/commands/GoogleImagenCommand.py
syrius/commands/GoogleTextToSpeechCommand.py
syrius/commands/GrtCommand.py
syrius/commands/IdeogramGenerateImageCommand.py
syrius/commands/IfCommand.py
syrius/commands/JoinAudioCommand.py
syrius/commands/LoopInputCommand.py
syrius/commands/LumaImageToVideoCommand.py
syrius/commands/LumaTextToVideoCommand.py
syrius/commands/OCRToMarkdownCommand.py
syrius/commands/OpenAIChatCommand.py
syrius/commands/OpenAICompletionCommand.py
syrius/commands/OpenAITextToSpeechCommand.py
syrius_sdk-0.2.87.dist-info/METADATA
syrius_sdk-0.2.87.dist-info/WHEEL
syrius_sdk-0.2.87.dist-info/top_level.txt
syrius_sdk-0.2.87.dist-info/RECORD
